pydan/ansi.py
pydan/api.py
pydan/jdata.py
pydan/log.py
pydan/logsmart.py
pydan/logsmartold.py
pydan/muid.py
pydan/run.py
pydan/script.py
pydan/utils.py
pydan/venv.py
pydan/xdata.py
pydan-8.dist-info/METADATA
pydan-8.dist-info/WHEEL
pydan-8.dist-info/top_level.txt
pydan-8.dist-info/RECORD
