Metadata-Version: 2.1
Name: pydan
Version: 8
Summary: Python3 Data Utils
Author: Jose Biosca
Author-email: jose@biosca.eu
License: MIT
Classifier: Development Status :: 5 - Production/Stable
Classifier: License :: OSI Approved :: MIT License
Requires-Python: >=3.6
